hashauthenticator/__init__.py
hashauthenticator/hashauthenticator.py
hashauthenticator/passwordhash.py
jupyterhub_hashauthenticator-0.5.0.data/scripts/hashauthpw
jupyterhub_hashauthenticator-0.5.0.dist-info/LICENSE
jupyterhub_hashauthenticator-0.5.0.dist-info/METADATA
jupyterhub_hashauthenticator-0.5.0.dist-info/WHEEL
jupyterhub_hashauthenticator-0.5.0.dist-info/top_level.txt
jupyterhub_hashauthenticator-0.5.0.dist-info/RECORD
