Metadata-Version: 2.1
Name: jupyterhub-hashauthenticator
Version: 0.5.0
Summary: Hashed Password Authenticator for JupyterHub
Home-page: https://github.com/thedataincubator/jupyterhub-hashauthenticator
Author: Petko Minkov
Author-email: pminkov@gmail.com
Maintainer: Robert Schroll
Maintainer-email: robert@thedataincubator.com
License: BSD3
Platform: UNKNOWN
Requires-Dist: jupyterhub
Requires-Dist: tornado
Requires-Dist: traitlets
Requires-Dist: oauthenticator
